fuzzic/fuzzic_cli.py
fuzzic/configuration/.gitkeep
fuzzic/configuration/__init__.py
fuzzic/configuration/config.py
fuzzic/data_management/.gitkeep
fuzzic/data_management/__init__.py
fuzzic/data_management/export_manager.py
fuzzic/data_management/import_manager.py
fuzzic/interpretability/.gitkeep
fuzzic/interpretability/__init__.py
fuzzic/interpretability/fuzzy_logic_manager.py
fuzzic/interpretability/interpretability_manager.py
fuzzic/interpretability/rulebase.py
fuzzic/interpretability/criteria/.gitkeep
fuzzic/interpretability/criteria/__init__.py
fuzzic/interpretability/criteria/complementarity.py
fuzzic/interpretability/criteria/completeness.py
fuzzic/interpretability/criteria/conclusion_size.py
fuzzic/interpretability/criteria/consistency.py
fuzzic/interpretability/criteria/convexity.py
fuzzic/interpretability/criteria/coverage.py
fuzzic/interpretability/criteria/distinguishability.py
fuzzic/interpretability/criteria/extrema.py
fuzzic/interpretability/criteria/justifiable_number_of_elements.py
fuzzic/interpretability/criteria/membership_function_sharing.py
fuzzic/interpretability/criteria/normality.py
fuzzic/interpretability/criteria/number_of_rules.py
fuzzic/interpretability/criteria/number_of_variables.py
fuzzic/interpretability/criteria/number_rules_activated.py
fuzzic/interpretability/criteria/premisse_size.py
fuzzic/interpretability/criteria/preservation_order.py
fuzzic/interpretability/criteria/prototype.py
fuzzic/interpretability/criteria/rule_size.py
fuzzic/interpretability/criteria/uniformity.py
fuzzic/interpretability/criteria/unimodality.py
fuzzic/study/.gitkeep
fuzzic/study/__init__.py
fuzzic/study/study.py
fuzzic/visualization/.gitkeep
fuzzic/visualization/__init__.py
fuzzic/visualization/dashboard.py
fuzzic/visualization/fuzzic.jpg
fuzzic/visualization/plot.py
fuzzic-0.5.1.dist-info/licenses/LICENSE
fuzzic-0.5.1.dist-info/METADATA
fuzzic-0.5.1.dist-info/WHEEL
fuzzic-0.5.1.dist-info/entry_points.txt
fuzzic-0.5.1.dist-info/top_level.txt
fuzzic-0.5.1.dist-info/RECORD
