Metadata-Version: 2.4
Name: fuzzic
Version: 0.5.1
Summary: FuzzIC is a Python library for evaluating the interpretability of fuzzy rule bases.
Author-email: Thomas Pontoizeau <thomas.pontoizeau@lip6.fr>
Project-URL: Homepage, https://gitlab.lip6.fr/pontoizeau/fuzzic
Project-URL: Issues, https://gitlab.lip6.fr/pontoizeau/fuzzic/-/issues
Project-URL: Repository, https://gitlab.lip6.fr/pontoizeau/fuzzic.git
Keywords: fuzzy inference systems,interpretable ai,interpretability measure,explainable ai
Classifier: Programming Language :: Python :: 3
Classifier: Programming Language :: Python :: 3 :: Only
Classifier: Operating System :: OS Independent
Classifier: Intended Audience :: Science/Research
Classifier: Topic :: Scientific/Engineering :: Artificial Intelligence
Classifier: Topic :: Scientific/Engineering :: Mathematics
Requires-Python: >=3.10
License-File: LICENSE
Requires-Dist: numpy
Requires-Dist: matplotlib
Dynamic: license-file
